ntfy_lite/__init__.py
ntfy_lite/actions.py
ntfy_lite/defaults.py
ntfy_lite/demo_logging.py
ntfy_lite/demo_push.py
ntfy_lite/error.py
ntfy_lite/handler.py
ntfy_lite/ntfy.py
ntfy_lite/ntfy2logging.py
ntfy_lite/py.typed
ntfy_lite/utils.py
ntfy_lite/version.py
ntfy_lite-1.0.3.dist-info/LICENSE
ntfy_lite-1.0.3.dist-info/METADATA
ntfy_lite-1.0.3.dist-info/WHEEL
ntfy_lite-1.0.3.dist-info/entry_points.txt
ntfy_lite-1.0.3.dist-info/RECORD
