Metadata-Version: 2.1
Name: ntfy-lite
Version: 1.0.3
Summary: minimalistic python API for sending ntfy notifications
License: BSD-3-Clause
Author: Vincent Berenz
Author-email: vberenz@tuebingen.mpg.de
Requires-Python: >3.8.1,<4
Classifier: License :: OSI Approved :: BSD License
Classifier: Programming Language :: Python :: 3
Classifier: Programming Language :: Python :: 3.9
Classifier: Programming Language :: Python :: 3.10
Classifier: Programming Language :: Python :: 3.11
Requires-Dist: pandas (>=2.0.0,<3.0.0)
Requires-Dist: requests (>=2.28.2,<3.0.0)
Requires-Dist: validators (>=0.20.0,<0.21.0)
